isp_vmmanager_sdk
