Metadata-Version: 1.0
Name: isp-vmmanager-sdk
Version: 1.3.2
Summary: ISP VmManager Python SDK
Home-page: https://github.com/Underlor/isp_vmmanager_sdk
Author: Underlor
Author-email: cfyz_74@mail.ru
License: Creative Commons Attribution-Noncommercial-Share Alike license
Platform: UNKNOWN
